odoo8_addon_account_invoice_partner-8.0.0.2.0.99.dev13-py2.7-nspkg.pth
odoo8_addon_account_invoice_partner-8.0.0.2.0.99.dev13.dist-info/METADATA
odoo8_addon_account_invoice_partner-8.0.0.2.0.99.dev13.dist-info/RECORD
odoo8_addon_account_invoice_partner-8.0.0.2.0.99.dev13.dist-info/WHEEL
odoo8_addon_account_invoice_partner-8.0.0.2.0.99.dev13.dist-info/namespace_packages.txt
odoo8_addon_account_invoice_partner-8.0.0.2.0.99.dev13.dist-info/top_level.txt
odoo_addons/account_invoice_partner/README.md
odoo_addons/account_invoice_partner/__init__.py
odoo_addons/account_invoice_partner/__openerp__.py
odoo_addons/account_invoice_partner/i18n/account_invoice_partner.pot
odoo_addons/account_invoice_partner/i18n/ar.po
odoo_addons/account_invoice_partner/i18n/bg.po
odoo_addons/account_invoice_partner/i18n/bs.po
odoo_addons/account_invoice_partner/i18n/ca.po
odoo_addons/account_invoice_partner/i18n/cs.po
odoo_addons/account_invoice_partner/i18n/de.po
odoo_addons/account_invoice_partner/i18n/el_GR.po
odoo_addons/account_invoice_partner/i18n/en_GB.po
odoo_addons/account_invoice_partner/i18n/es.po
odoo_addons/account_invoice_partner/i18n/es_CR.po
odoo_addons/account_invoice_partner/i18n/es_EC.po
odoo_addons/account_invoice_partner/i18n/es_MX.po
odoo_addons/account_invoice_partner/i18n/es_PE.po
odoo_addons/account_invoice_partner/i18n/et.po
odoo_addons/account_invoice_partner/i18n/fi.po
odoo_addons/account_invoice_partner/i18n/fr.po
odoo_addons/account_invoice_partner/i18n/fr_CA.po
odoo_addons/account_invoice_partner/i18n/fr_CH.po
odoo_addons/account_invoice_partner/i18n/gl.po
odoo_addons/account_invoice_partner/i18n/hr.po
odoo_addons/account_invoice_partner/i18n/hr_HR.po
odoo_addons/account_invoice_partner/i18n/hu.po
odoo_addons/account_invoice_partner/i18n/id.po
odoo_addons/account_invoice_partner/i18n/it.po
odoo_addons/account_invoice_partner/i18n/ja.po
odoo_addons/account_invoice_partner/i18n/lt.po
odoo_addons/account_invoice_partner/i18n/mk.po
odoo_addons/account_invoice_partner/i18n/mn.po
odoo_addons/account_invoice_partner/i18n/nb.po
odoo_addons/account_invoice_partner/i18n/nb_NO.po
odoo_addons/account_invoice_partner/i18n/nl.po
odoo_addons/account_invoice_partner/i18n/nl_BE.po
odoo_addons/account_invoice_partner/i18n/nl_NL.po
odoo_addons/account_invoice_partner/i18n/pl.po
