Metadata-Version: 2.1
Name: odoo8-addon-account-invoice-partner
Version: 8.0.0.2.0.99.dev13
Summary: Automatically select invoicing partner on invoice
Home-page: https://github.com/OCA/account-invoicing
Author: Therp BV,Odoo Community Association (OCA)
Author-email: support@odoo-community.org
License: AGPL-3
Platform: UNKNOWN
Classifier: Programming Language :: Python
Classifier: Framework :: Odoo
Classifier: License :: OSI Approved :: GNU Affero General Public License v3
Requires-Python: ~=2.7
Requires-Dist: odoo (<9.0a,>=8.0a)
